LICENSE
MANIFEST.in
README.rst
setup.py
django_logical_rules.egg-info/PKG-INFO
django_logical_rules.egg-info/SOURCES.txt
django_logical_rules.egg-info/dependency_links.txt
django_logical_rules.egg-info/requires.txt
django_logical_rules.egg-info/top_level.txt
logical_rules/__init__.py
logical_rules/helpers.py
logical_rules/mixins.py
logical_rules/models.py
logical_rules/register.py
logical_rules/rules.py
logical_rules/templatetags/__init__.py
logical_rules/templatetags/logical_rules_tags.py
logical_rules/tests/__init__.py
logical_rules/tests/testMixin.py
logical_rules/tests/testRegister.py
logical_rules/tests/testTags.py
logical_rules/tests/test_app/__init__.py
logical_rules/tests/test_app/models.py
logical_rules/tests/test_app/rules.py
logical_rules/tests/test_app/urls.py
logical_rules/tests/test_app/views.py