Metadata-Version: 1.1
Name: django-logical-rules
Version: 1.0
Summary: A rule engine for Django apps.
Home-page: https://bitbucket.org/aashe/django-logical-rules
Author: Benjamin Stookey
Author-email: ben@aashe.org
License: LICENSE
Platform: UNKNOWN
Classifier: Development Status :: 4 - Beta
Classifier: Environment :: Web Environment
Classifier: Framework :: Django
Classifier: Intended Audience :: Developers
Classifier: License :: OSI Approved :: BSD License
Classifier: Operating System :: OS Independent
Classifier: Programming Language :: Python
Classifier: Topic :: Utilities
